{
  "source": "ABC",
  "title": "Man guilty of killing woman and her daughter to be Florida's 7th execution of 2026",
  "url": "https://abcnews.com/US/wireStory/man-guilty-killing-woman-daughter-set-floridas-7th-133174780",
  "published": "Thu, 21 May 2026 08:15:47 -0400",
  "full_text": "Man guilty of killing woman and her daughter to be Florida's 7th execution of 2026\nA Florida man convicted of fatally stabbing of his cousin’s girlfriend and the couple's 4-year-old daughter is set to be executed\nSTARKE, Fla. -- A Florida man convicted of fatally stabbing of his cousin’s girlfriend and the couple's 4-year-old daughter is set to be executed Thursday evening.\nRichard Knight, 47, is scheduled to receive a three-drug injection starting at 6 p.m. at Florida State Prison near Starke. Knight was sentenced to death after being convicted of two counts of first-degree murder in 2006 for the deaths of Odessia Stephens and her four-year-old child, Hanessia Mullings.\nThis would be Florida’s seventh execution so far this year, following a record 19 executions in 2025. Republican Gov. Ron DeSantis oversaw more executions in a single year in 2025 than any other Florida governor since the death penalty was reinstated in 1976. The previous record was set in 2014 with eight executions.\nAccording to court records, Knight had been living in Coral Springs, near Fort Lauderdale, with his cousin, his cousin's girlfriend and their daughter in June 2000. Knight and Stephens frequently argued about Knight living there. One evening while Knight's cousin was at work, Stephens told Knight that he would need to move out the next morning. Knight became angry and stabbed Stephens multiple times and then attacked the young girl, officials said.\nWhile being held at the Broward County Jail following his arrest, Knight confessed the killings to another inmate, who testified against Knight during his trial.\nThe Florida Supreme Court denied Knight's appeals last Friday. The court rejected his claim of newly discovered evidence, pointing out that an unidentified fingerprint found on a knife at the murder scene was known about and addressed during Knight's original trial. The court also rejected claims based on Florida's execution protocols and warrant process.\nA final appeal was still pending before the U.S. Supreme Court.\nA total of 47 people were executed in the U.S. in 2025. Florida led the way with a flurry of death warrants signed by DeSantis. Alabama, South Carolina and Texas tied for second with five executions each.\nAn execution was scheduled for Thursday in Tennessee. And another execution is planned in Florida on June 2. Andrew Richard Lukehart, 53, was convicted of fatally beating of his girlfriend's infant daughter in 1996.\nAll Florida executions are carried out via lethal injection of a sedative, a paralytic and a drug that stops the heart, according to the Department of Corrections."
}