{
  "source": "ABC",
  "title": "WATCH:  Quadriplegic U.S. army veteran surprised with life-changing gift",
  "url": "https://abcnews.com/video/133255347/",
  "published": "Sat, 23 May 2026 19:14:56 -0400",
  "full_text": "Quadriplegic U.S. army veteran surprised with life-changing gift\nA U.S. army veteran injured in the line of duty and his family receive accessible vehicle from the Gary Sinise Foundation and Wells Fargo.\nMay 23, 2026\nAdditional Live Streams\nAdditional Live Streams\nTop Stories\nTop Stories\nTrump renews calls for White House ballroom\nMay 24, 2026Dramatic cave rescue in upstate New York\nMay 24, 2026State of emergency declared in Southern California\nMay 24, 2026Africa grapples with deadly Ebola outbreak\nMay 24, 2026Stampede at a South Carolina bike festival\nMay 24, 2026US, Iran inch closer to peace deal\nMay 24, 2026Trump's latest attempt toward a possible interim agreement to reopen Strait of Hormuz\nMay 24, 2026Suspect dead after exchange of gunfire near White House: Secret Service\nMay 24, 2026Russia launching heavy attack on Russia from air, sea and land\nMay 24, 2026Kyle Busch cause of death revealed\nMay 24, 2026Knicks take commanding lead in Cavaliers series\nMay 24, 2026Officials sounding the alarm on AI vacation scams\nMay 24, 2026Trump: deal with Iran is 'largely negotiated'\nMay 23, 2026Growing fears chemical plant could explode\nMay 23, 20261 killed in shipyard explosions on Staten Island\nMay 23, 2026Remembering hip-hop artist Rob Base\nMay 23, 2026Race to contain Ebola outbreak in Central Africa\nMay 23, 20266.0 quake rocks Hawaii's Big Island\nMay 23, 20267-year-old becomes the youngest to summit El Capitan\nMay 23, 2026Successful SpaceX launch\nMay 23, 2026Deadly coal mine explosion in China\nMay 23, 2026Potential gas and oil crisis\nMay 23, 2026Rising gas prices impact millions for Memorial Day weekend\nMay 23, 2026Washout for millions on the move\nMay 23, 2026Weight-loss drug shows breakthrough results\nMay 23, 2026Wedding ring recovered after Simi Valley fire\nMay 23, 2026Tips for getting ahead of the busy holiday weekend\nMay 23, 2026Memorial Day travelers hit roads and skies despite rising costs\nMay 23, 2026Parent shares warning signs after child’s stroke\nMay 23, 2026Toxic chemical leak forces evacuations in Southern California\nMay 22, 2026\nABC News Live Presents\nABC News Live Presents\nBuilding A.I.: The Deep Mind Behind the Moment\nMay 22, 2026All Access with Linsey Davis: Neil deGrasse Tyson\nMay 18, 2026All Access with Linsey Davis: Lisa Kudrow\nMay 11, 2026All Access with Linsey Davis: Justice Neil Gorsuch\nMay 06, 2026All Access with Linsey Davis: Emma Grede\nApr 20, 2026All Access with Linsey Davis: Bob Odenkirk\nApr 13, 2026Dolores Huerta: Her Words, Her Movement\nMar 22, 2026My Reality: The American Dream\nFeb 23, 2026AI: The Next Chapter\nFeb 06, 2026All Access with Linsey Davis: Stephen A. Smith\nJan 12, 2026Daddy Yankee: A Higher Note\nNov 20, 2025Gut Check: The Foods We Eat\nNov 19, 2025All Access With Linsey Davis: Stevie Van Zandt\nNov 18, 2025All Access with Linsey Davis: Andrew Cuomo\nOct 30, 2025All Access With Linsey Davis: Zohran Mamdani\nOct 27, 2025Springsteen: Deliver Me from Nowhere - A Conversation with the Cast\nOct 21, 2025All Access With Linsey Davis: Jeremy Allen White\nOct 20, 2025The Children of Gaza\nOct 11, 2025Glen Powell and Eli Manning: ABC News Live Prime with Linsey Davis\nOct 06, 2025The Playlist Presents: Dale Play!\nSep 26, 2025The Queens: Chaka Khan, Patti LaBelle & Stephanie Mills\nSep 18, 2025War or Peace: The Zelenskyy Interview | Martha Raddatz Reports\nSep 08, 2025Linsey Davis Reports: The Epstein Survivors Speak Out\nSep 03, 2025Backstage Pass - The Fantastic Four: First Steps\nJul 25, 2025After the Ashes: Rebuilding from the LA Wildfires\nJul 10, 2025Celebrating 20 Years of Shondaland\nJul 04, 2025Operation Babylift: The 50-Year Journey – A Special Edition of 20/20\nMay 08, 2025Our Home: Local Action and Global Impact\nApr 22, 2025America’s Care Crisis\nFeb 13, 2025Immigration Crackdown\nFeb 12, 2025\nABC News Specials on\nBarbara Walters: Tell Me Everything\nAug 08, 2025Impact X Nightline: On the Brink\nDec 14, 2023Impact X Nightline: Unboxing Shein\nNov 27, 2023The Lady Bird Diaries\nNov 27, 2023Impact X Nightline: It's Britney\nNov 27, 2023Impact X Nightline: Natalee Holloway -- A Killer Confesses\nNov 27, 2023Impact X Nightline: Who Shot Tupac?\nNov 27, 2023Wild Crime\nOct 26, 2022Impact x Nightline\nOct 28, 2022Power Trip: Those Who Seek Power and Those Who Chase Them\nSep 27, 2022The Murders Before the Marathon\nSep 01, 2022The Ivana Trump Story: The First Wife\nJul 25, 2022Aftershock\nJul 18, 2022Mormon No More\nJun 22, 2022Leave No Trace: A Hidden History of the Boy Scouts\nJun 15, 2022Keeper of the Ashes: The Oklahoma Girl Scout Murders\nMay 20, 2022The Orphans of COVID: America's Hidden Toll\nMay 13, 2022Superstar: Patrick Swayze\nApr 14, 2022The Kardashians -- An ABC News Special\nApr 05, 202224 Months That Changed the World\nMar 30, 2022"
}