{
  "source": "AlJazeera",
  "title": "Subdued Lebanon Liberation Day celebrations under new Israeli occupation",
  "url": "https://www.aljazeera.com/features/2026/5/25/subdued-lebanon-liberation-day-celebrations-under-new-israeli-occupation?traffic_source=rss",
  "published": "Mon, 25 May 2026 17:39:54 +0000",
  "full_text": "Subdued Lebanon Liberation Day celebrations under new Israeli occupation\nTwenty-six years after Israeli forces were driven out of southern Lebanon, fears of a new occupation have emerged.\nBeirut, Lebanon – On May 25, 2000, the last Israeli troops withdrew from southern Lebanon ending their 18-year occupation.\nThis expulsion of Israeli forces by an armed movement led by Hezbollah has been a cause of national celebration in Lebanon ever since, but this year, a new occupation in the south has dampened the mood.\n“Liberation Day is a sacred day for us,” Ali Saleh, 55, from Jwaya in southern Lebanon told Al Jazeera. “It is a holiday of victory, pride and dignity.”\nSaleh said he would spend this Liberation Day at the Camille Chamoun Stadium on the southern periphery of Beirut, where he has lived with his wife and son after being displaced in March, when Israeli forces again invaded the south.\nHe is one of more than 1.2 million people in Lebanon who have been displaced from their homes, predominantly from south Lebanon and Beirut’s southern suburbs, since then.\nIn the past two years, Lebanon has been invaded twice by Israel. In early 2025, more than two months after a ceasefire was agreed, the Israeli military withdrew from all but five points in south Lebanon. This time, however, many Lebanese fear history is repeating itself, and that a protracted Israeli occupation of the the country has started again.\n“He who didn’t live in southern Lebanon before 2000 didn’t know what it means to live under occupation,” Saleh said. “Liberation Day broke our shackles, freed the precious land, freed the plants, freed the butterflies, the birds, every grain of dust. It freed everything.”\nConflicting speeches on Liberation\nDuring the Lebanese civil war (1975-1990), Israel twice invaded the country – in 1978 and 1982 – to eject the Palestine Liberation Organisation (PLO) from the country.\nIsraeli forces reached as far as Beirut in 1982, forcing PLO fighters from Lebanon. But the Israelis continued to occupy large parts of southern Lebanon, until they were driven out in 2000, following a persistent campaign by Hezbollah. The recent Israeli invasion brought back memories of those years of occupation for southerners.\n“There is a pain in my heart because this holiday is not complete,” Saleh said. “We are living in a body without a soul. Our soul is south and our body is here. I wish that this Eid we would be celebrating on our land.”\nIn the early hours of March 2, Hezbollah fired rockets at Israeli targets for the first time in over a year in retaliation for the killing of Iran’s Supreme Leader, Ayatollah Ali Khamenei.\nDespite a November 2024 ceasefire, Israel had not stopped attacking Lebanon, but took advantage of the Hezbollah assault to launch a new wave of devastating attacks across the country and a ground invasion of the south.\nSince March 2, Israel has killed 3,151 people in Lebanon, according to Lebanon’s Ministry of Public Health.\nUS President Donald Trump announced a ceasefire on April 16, and extended into early July. That has eased attacks on Beirut and its suburbs, but the assault on the south has continued, killing paramedics and civilians.\nOn a daily basis, Israel has issued new forced evacuation orders for towns and villages in the south. Hezbollah has launched its own attacks on Israeli targets inside Lebanon, and in Israel, including using fibre optic drones which are immune to Israeli jamming.\nIn a speech to mark Liberation Day on Monday, Lebanon’s President, Joseph Aoun, said that southern Lebanon “wrote an unprecedented chapter when the Israeli occupation withdrew as a result of the steadfastness and sacrifices of the people of this land, making May 25 a day of national dignity”.\nUnder Aoun’s command, Beirut is engaging in direct talks with Israel for the first time, and despite the controversial nature of the negotiations, he insists the government will not compromise on its goal of achieving a “full Israeli withdrawal” from southern Lebanon.\nPrime Minister Nawaf Salam wrote on X that “we will not celebrate [the holiday] until the day of Israel’s complete withdrawal from our land and the safe and dignified return of our people”.\nHezbollah response\nHezbollah has repeatedly clashed with the government’s position, saying it rejects direct negotiations with Israel and prefers talks via intermediaries instead.\nIn a televised address on Sunday, Hezbollah’s Secretary-General Naim Qassem repeated his rejection of direct negotiations: “Indirect negotiations are preferable. Return to national dialogue and internal solutions rather than aligning with the United States and Israel.”\nHe also fueled controversy over increasing tensions inside Lebanon, for the first time suggesting that the Lebanese government should step down if it cannot fulfil its duties.\n“If this government cannot protect sovereignty, it should resign,” Qassem said.\nQassem’s statement drew strong condemnation from the United States State Department.\nIran has reportedly included a ceasefire in Lebanon as part of its conditions to end the war with the US and Israel. However, Israeli Prime Minister Benjamin Netanyahu is believed to be eager to continue the war, and has been urged by his right-wing ministers to resume attacks on Beirut, where drones buzzed low overhead all day Sunday and Monday.\nIn search of “another victory”\nOn Monday, as banks and offices closed for the annual Liberation Day holiday, Israeli air raids killed three people in southern Lebanon and more evacuation orders were issued for 10 towns and villages.\nHomes near the port city of Tyre in southern Lebanon were also struck, along with eight other towns in the south.\n“What are we supposed to do,” Hussein told Al Jazeera. He is from Qlayleh but displaced at a school in Tyre. “There are warnings [to evacuate homes] all over [the area].”\nDrones were reported flying over the Baalbek region in Lebanon’s east, another area that has come under sustained Israeli attacks since the ceasefire last month.\nUnder such conditions, many in Lebanon feel that this Liberation Day, which is usually marked with celebrations, comes at a sombre moment for the country.\nSaleh, the man from Jwaya, said he had hoped to see southern Lebanon liberated, and Lebanese citizens held in Israeli detention facilities released.\nNabil, from Markaba, a border town largely destroyed since Israel set up a military outpost there, has been living in a school in the Ras Beirut neighbourhood since March 2, but remains hopeful and defiant.\n“We are very proud that it is Liberation Day and that we expelled the Israeli enemy from Lebanon,” he said. “We took our areas and took everything and our house in 2000, and God willing, there will be another victory.”"
}